{
  "id": "b0079708-7b0c-4ebb-b818-e06a791e870f",
  "userId": "user_37hSb40YjPzeYW6e9IJSmKrnJIH",
  "username": "Aksh",
  "question": {
    "url": "https://leetcode.com/problems/rotate-string/description/",
    "title": "812. Rotate String"
  },
  "difficulty": 1.5,
  "tags": [
    "String",
    "String Matching"
  ],
  "notes": "Adding the string to itself and using find function makes the solution much more efficient.\r\nTC(concat, sol2) = O(n) but TC(brute_force, sol1) = O(n^2).\r\nSC = O(n) for both.",
  "timestamp": "2026-01-12T18:53:04.133Z",
  "mainSolution": {
    "path": "data/submissions/2026/01/2026-01-12_812RotateString_Aksh_b0079708-7b0c-4ebb-b818-e06a791e870f.txt",
    "extension": "txt"
  },
  "alternateSolution": {
    "label": "Concatenation to avoid brute force",
    "path": "data/submissions/2026/01/2026-01-12_812RotateString_Aksh_b0079708-7b0c-4ebb-b818-e06a791e870f_alt.txt",
    "extension": "txt"
  },
  "platform": "leetcode",
  "enrichment": {
    "realTitle": "812. Rotate String",
    "difficultyLabel": "Easy"
  }
}